odoo10_addon_shopinvader_invoice-10.0.1.2.5-nspkg.pth
odoo/addons/shopinvader_invoice/README.rst
odoo/addons/shopinvader_invoice/__init__.py
odoo/addons/shopinvader_invoice/__manifest__.py
odoo/addons/shopinvader_invoice/readme/CONTRIBUTORS.rst
odoo/addons/shopinvader_invoice/readme/DESCRIPTION.rst
odoo/addons/shopinvader_invoice/services/__init__.py
odoo/addons/shopinvader_invoice/services/invoice.py
odoo/addons/shopinvader_invoice/static/description/index.html
odoo/addons/shopinvader_invoice/tests/__init__.py
odoo/addons/shopinvader_invoice/tests/common.py
odoo/addons/shopinvader_invoice/tests/test_invoice_service.py
odoo10_addon_shopinvader_invoice-10.0.1.2.5.dist-info/METADATA
odoo10_addon_shopinvader_invoice-10.0.1.2.5.dist-info/WHEEL
odoo10_addon_shopinvader_invoice-10.0.1.2.5.dist-info/namespace_packages.txt
odoo10_addon_shopinvader_invoice-10.0.1.2.5.dist-info/top_level.txt
odoo10_addon_shopinvader_invoice-10.0.1.2.5.dist-info/RECORD
