Metadata-Version: 2.1
Name: odoo10-addon-shopinvader-invoice
Version: 10.0.1.2.5
Summary: Shopinvader Invoice module
Home-page: https://shopinvader.com
Author: ACSONE SA/NV
License: AGPL-3
Platform: UNKNOWN
Classifier: Programming Language :: Python
Classifier: Framework :: Odoo
Classifier: License :: OSI Approved :: GNU Affero General Public License v3
Requires-Python: ~=2.7
Requires-Dist: odoo10-addon-shopinvader
Requires-Dist: odoo (<10.1dev,>=10.0)
